distributed_transcoder_common/__init__.py
distributed_transcoder_common/message_types.py
distributed_transcoder_common/models.py
distributed_transcoder_common-0.2.12.dist-info/METADATA
distributed_transcoder_common-0.2.12.dist-info/WHEEL
distributed_transcoder_common-0.2.12.dist-info/RECORD
